victronvenusclient/__about__.py
victronvenusclient/__init__.py
victronvenusclient/_topic_map.py
victronvenusclient/_unwrappers.py
victronvenusclient/constants.py
victronvenusclient/data_classes.py
victronvenusclient/device.py
victronvenusclient/hub.py
victronvenusclient/metric.py
victronvenusclient/utils/__init__.py
victronvenusclient/utils/dump_mqtt.py
victronvenusclient/utils/view_metrics.py
victronvenusclient-0.1.3.dist-info/METADATA
victronvenusclient-0.1.3.dist-info/WHEEL
victronvenusclient-0.1.3.dist-info/licenses/LICENSE.txt
victronvenusclient-0.1.3.dist-info/RECORD
