Metadata-Version: 2.4
Name: victronvenusclient
Version: 0.1.3
Summary: An async MQTT Victron Venus OS client library.
Project-URL: Documentation, https://github.com/JohansLab/victronvenusclient#readme
Project-URL: Issues, https://github.com/JohansLab/victronvenusclient/issues
Project-URL: Source, https://github.com/JohansLab/victronvenusclient
Author-email: Johan du Plessis <johan@epicwin.co.za>
License-Expression: MIT
License-File: LICENSE.txt
Classifier: Development Status :: 4 - Beta
Classifier: Programming Language :: Python
Classifier: Programming Language :: Python :: 3.9
Classifier: Programming Language :: Python :: 3.10
Classifier: Programming Language :: Python :: 3.11
Classifier: Programming Language :: Python :: 3.12
Classifier: Programming Language :: Python :: Implementation :: CPython
Classifier: Programming Language :: Python :: Implementation :: PyPy
Requires-Python: >=3.9
Requires-Dist: gmqtt>=0.7.0
